ezml/__init__.py
ezml/data.py
ezml/diagnostic.py
ezml/main.py
ezml/model.py
ezml/pipeline.py
ds_best_practice_example-0.1.1.dist-info/LICENSE
ds_best_practice_example-0.1.1.dist-info/METADATA
ds_best_practice_example-0.1.1.dist-info/WHEEL
ds_best_practice_example-0.1.1.dist-info/entry_points.txt
ds_best_practice_example-0.1.1.dist-info/RECORD
