Metadata-Version: 2.1
Name: ds-best-practice-example
Version: 0.1.1
Summary: Showcase best practices for structuring a Python package.
Home-page: https://github.com/cheeyeelim/ds-best-practice-example
License: BSD-3-Clause
Author: Chee Yee Lim
Author-email: cheeyee.lim@gmail.com
Requires-Python: >=3.9,<3.10
Classifier: Development Status :: 2 - Pre-Alpha
Classifier: Intended Audience :: Developers
Classifier: License :: OSI Approved :: BSD License
Classifier: Natural Language :: English
Classifier: Programming Language :: Python :: 3
Classifier: Programming Language :: Python :: 3.9
Provides-Extra: dev
Provides-Extra: doc
Provides-Extra: test
Requires-Dist: black (>=21.5b2,<22.0) ; extra == "test"
Requires-Dist: bump2version (>=1.0.1,<2.0.0) ; extra == "dev"
Requires-Dist: flake8 (>=3.9.2,<4.0.0) ; extra == "test"
Requires-Dist: flake8-docstrings (>=1.6.0,<2.0.0) ; extra == "test"
Requires-Dist: hydra-core (>=1.3.2,<2.0.0)
Requires-Dist: hypothesis (>=6.82.3,<7.0.0) ; extra == "test"
Requires-Dist: ipykernel (>=6.25.1,<7.0.0) ; extra == "dev"
Requires-Dist: isort (>=5.8.0,<6.0.0) ; extra == "test"
Requires-Dist: mike (>=1.1.2,<2.0.0) ; extra == "doc"
Requires-Dist: mkdocs (>=1.5.2,<2.0.0) ; extra == "doc"
Requires-Dist: mkdocs-autorefs (>=0.5.0,<0.6.0) ; extra == "doc"
Requires-Dist: mkdocs-git-revision-date-plugin (>=0.3.2,<0.4.0) ; extra == "doc"
Requires-Dist: mkdocs-include-markdown-plugin (>=6.0.0,<7.0.0) ; extra == "doc"
Requires-Dist: mkdocs-material (>=9.1.21,<10.0.0) ; extra == "doc"
Requires-Dist: mkdocs-material-extensions (>=1.1.1,<2.0.0)
Requires-Dist: mkdocstrings (>=0.22.0,<0.23.0) ; extra == "doc"
Requires-Dist: mkdocstrings-python (>=1.3.0,<2.0.0) ; extra == "doc"
Requires-Dist: mypy (>=0.900,<0.901) ; extra == "test"
Requires-Dist: pandas (>=2.0.3,<3.0.0)
Requires-Dist: pip (>=23.2.1,<24.0.0)
Requires-Dist: pre-commit (>=2.12.0,<3.0.0) ; extra == "dev"
Requires-Dist: pytest (>=7.4.0,<8.0.0) ; extra == "test"
Requires-Dist: pytest-cov (>=4.1.0,<5.0.0) ; extra == "test"
Requires-Dist: pytest-timeout (>=2.1.0,<3.0.0) ; extra == "test"
Requires-Dist: scikit-learn (>=1.3.0,<2.0.0)
Requires-Dist: setuptools (>=68.0.0,<69.0.0)
Requires-Dist: toml (>=0.10.2,<0.11.0) ; extra == "dev"
Requires-Dist: tox (>=4.7.0,<5.0.0) ; extra == "dev"
Requires-Dist: twine (>=3.3.0,<4.0.0) ; extra == "dev"
Requires-Dist: virtualenv (>=20.24.3,<21.0.0) ; extra == "dev"
